{"name":"build-javascript","namedChunkGroups":{"app":{"name":"app","assets":[{"name":"webpack-runtime-dc7c352be710f4928ce4.js","size":3966},{"name":"framework-2bbaf5d7bbbad01da045.js","size":140992},{"name":"app-6817cd12a61e9f99a712.js","size":361234}],"filteredAssets":0,"assetsSize":506192,"filteredAuxiliaryAssets":3,"auxiliaryAssetsSize":1919782},"component---src-pages-404-tsx":{"name":"component---src-pages-404-tsx","assets":[{"name":"component---src-pages-404-tsx-585214e1b7e6394c72c0.js","size":3094}],"filteredAssets":0,"assetsSize":3094,"filteredAuxiliaryAssets":1,"auxiliaryAssetsSize":9832},"component---src-pages-index-tsx":{"name":"component---src-pages-index-tsx","assets":[{"name":"e51429d4-86ee2a08c0a22a49859c.js","size":326113},{"name":"95b6d7fa-40e684cb51dd0cb752fb.js","size":150048},{"name":"component---src-pages-index-tsx-01fc1bda690b691e478a.js","size":401175}],"filteredAssets":0,"assetsSize":877336,"filteredAuxiliaryAssets":3,"auxiliaryAssetsSize":2577589}},"assetsByChunkName":{"app":["webpack-runtime-dc7c352be710f4928ce4.js","framework-2bbaf5d7bbbad01da045.js","app-6817cd12a61e9f99a712.js"],"component---src-pages-404-tsx":["component---src-pages-404-tsx-585214e1b7e6394c72c0.js"],"component---src-pages-index-tsx":["e51429d4-86ee2a08c0a22a49859c.js","95b6d7fa-40e684cb51dd0cb752fb.js","component---src-pages-index-tsx-01fc1bda690b691e478a.js"]},"childAssetsByChunkName":{}}